Metadata-Version: 2.1
Name: quicly-mongo
Version: 0.0.2
Summary: Quicly Mongo
Home-page: https://gitee.com/muxiaofei/quicly-mongo
Author: muxiaofei
Author-email: muxiaofei@gmail.com
License: UNKNOWN
Keywords: mongo
Platform: UNKNOWN
Classifier: Programming Language :: Python :: 3
Classifier: Programming Language :: Python :: 3.5
Classifier: Programming Language :: Python :: 3.6
Classifier: Programming Language :: Python :: 3.7
Classifier: Programming Language :: Python :: 3.8
Classifier: License :: OSI Approved :: MIT License
Classifier: Operating System :: OS Independent
